CHANGELOG
COPYRIGHT
INSTALL
LICENSE
MANIFEST.in
README
bank_ar.xml
setup.py
tryton.cfg
./__init__.py
./bank_ar.py
./bank_ar.xml
./tryton.cfg
./locale/es_AR.po
./tests/__init__.py
./tests/test_account_bank_ar.py
./view/bank_form.xml
./view/bank_tree.xml
./view/party_bank_form.xml
./view/party_bank_tree.xml
./view/party_form.xml
locale/es_AR.po
trytonar_account_bank_ar.egg-info/PKG-INFO
trytonar_account_bank_ar.egg-info/SOURCES.txt
trytonar_account_bank_ar.egg-info/dependency_links.txt
trytonar_account_bank_ar.egg-info/entry_points.txt
trytonar_account_bank_ar.egg-info/not-zip-safe
trytonar_account_bank_ar.egg-info/requires.txt
trytonar_account_bank_ar.egg-info/top_level.txt
view/bank_form.xml
view/bank_tree.xml
view/party_bank_form.xml
view/party_bank_tree.xml
view/party_form.xml