Metadata-Version: 1.1
Name: trytonar-account-bank-ar
Version: 3.4.0
Summary: Tryton module with banks of Argentina
Home-page: https://bitbucket.org/thymbra/account_bank_ar
Author: tryton-ar
Author-email: UNKNOWN
License: GPL-3
Platform: UNKNOWN
Classifier: Development Status :: 4 - Beta
Classifier: Environment :: Plugins
Classifier: Framework :: Tryton
Classifier: Intended Audience :: Developers
Classifier: Intended Audience :: Financial and Insurance Industry
Classifier: Intended Audience :: Legal Industry
Classifier: License :: OSI Approved :: GNU General Public License (GPL)
Classifier: Natural Language :: English
Classifier: Natural Language :: Spanish
Classifier: Operating System :: OS Independent
Classifier: Programming Language :: Python :: 2.7
Classifier: Topic :: Office/Business
Classifier: Topic :: Office/Business :: Financial :: Accounting
